hello.py
mcp_start-0.1.6.dist-info/METADATA
mcp_start-0.1.6.dist-info/WHEEL
mcp_start-0.1.6.dist-info/entry_points.txt
mcp_start-0.1.6.dist-info/top_level.txt
mcp_start-0.1.6.dist-info/RECORD
