Metadata-Version: 2.4
Name: mcp-start
Version: 0.1.6
Summary: Add your description here
Requires-Python: >=3.11
Requires-Dist: mcp[cli]==1.9.2
